<ti:work xmlns:ti="http://chs.harvard.edu/xmlns/cts"
         groupUrn="urn:cts:formulae:luzern"
         xml:lang="lat"
         urn="urn:cts:formulae:luzern.schiess0003">
   <ti:title xml:lang="lat">Quellenwerk zur Entstehung der Schweizerischen Eidgenossenschaft (Ed. Schiess) 9.3</ti:title>
   <ti:edition xmlns:dct="http://purl.org/dc/terms/"
               xmlns:cpt="http://purl.org/capitains/ns/1.0#"
               xmlns:dc="http://purl.org/dc/elements/1.1/"
               urn="urn:cts:formulae:luzern.schiess0003.lat001"
               workUrn="urn:cts:formulae:luzern.schiess0003">
      <ti:label xml:lang="lat">Quellenwerk zur Entstehung der Schweizerischen Eidgenossenschaft, 9.3</ti:label>
      <ti:description xml:lang="deu">Die Brüder Henger und Witowo schenken an das Kloster Luzern, dem Wichard vorsteht, ihren ganzen Besitz in der Mark Malters. Wer die Schenkung anfeindet, soll das Vierfache an den Ort geben und dem königlichen Fiskus 4 Unzen Gold, 12 π Silber bezahlen. Geschehen (5)45, in der 1. Indiktion, in der Vorhalle der Kirche, vor Vogt Engelger und zahlreichem Volk in den Tagen Kaiser Karls III.</ti:description>
      <cpt:structured-metadata xml:lang="deu">
         <dc:title>Quellenwerk zur Entstehung der Schweizerischen Eidgenossenschaft, 9.3</dc:title>
         <dct:abstract/>
         <dc:contributor>Pr. Dr. Philippe Depreux (Universität Hamburg)</dc:contributor>
         <dc:contributor>Franziska Quaas (Universität Hamburg)</dc:contributor>
         <dc:contributor>Dennis Lorenzen (Studentische Hilfskraft, Universität Hamburg)</dc:contributor>
         <dc:contributor>Dr. Matthew Munson (Universität Hamburg)</dc:contributor>
         <dc:contributor>Morgane Pica (Praktikantin, Ecole nationale des Chartes, Paris, Frankreich)</dc:contributor>
         <dc:editor>Traugott Schiess</dc:editor>
         <dct:dateCopyrighted>1933</dct:dateCopyrighted>
         <dct:bibliographicCitation>Traugott &lt;span class="surname"&gt;Schiess&lt;/span&gt;, Quellenwerk zur Entstehung der Schweizerischen Eidgenossenschaft, Aarau 1933, [URI: &lt;a target="_blank" href="http://d-nb.info/367663430"&gt;http://d-nb.info/367663430&lt;/a&gt;], S. 6.</dct:bibliographicCitation>
         <dct:temporal>Vor 840</dct:temporal>
         <dct:spatial/>
         <dc:publisher xml:lang="mul">Formulae-Litterae-Chartae Projekt</dc:publisher>
         <dc:format>application/tei+xml</dc:format>
         <dct:created>2018</dct:created>
      </cpt:structured-metadata>
   </ti:edition>
</ti:work>
